README.md
setup.py
bbchain/__init__.py
bbchain/__main__.py
bbchain/block.py
bbchain/blockchain.py
bbchain/main.py
bbchain/settings.py
bbchain/storage.py
bbchain/utils.py
bbchain.egg-info/PKG-INFO
bbchain.egg-info/SOURCES.txt
bbchain.egg-info/dependency_links.txt
bbchain.egg-info/entry_points.txt
bbchain.egg-info/top_level.txt
bbchain/consensus/__init__.py
bbchain/consensus/bft.py
bbchain/consensus/consensus.py
bbchain/consensus/dpos.py
bbchain/consensus/pos.py
bbchain/consensus/pow.py
bbchain/net/__init__.py
bbchain/net/network.py
bbchain/net/http/__init__.py
bbchain/net/http/base.py
bbchain/net/http/client.py
bbchain/net/http/master.py
bbchain/net/http/miner.py
bbchain/net/http/node.py