Metadata-Version: 1.1
Name: bbchain
Version: 0.1
Summary: Simple extendable Blockchain implemented in Python
Home-page: https://github.com/jepemo/basic-blockchain
Author: Jeremies Pérez Morata
Author-email: jeremiespm@gmail.com
License: GPL-v3
Keywords: blockchain,cryptocurrency
Platform: UNKNOWN
Classifier: Development Status :: 5 - Production/Stable
Classifier: Intended Audience :: Developers
Classifier: Intended Audience :: Developers
Classifier: Intended Audience :: Financial and Insurance Industry
Classifier: License :: OSI Approved :: GNU General Public License v3 (GPLv3)
Classifier: Programming Language :: Python :: 3
Classifier: Programming Language :: Python :: 3.3
Classifier: Programming Language :: Python :: 3.4
Classifier: Programming Language :: Python :: 3.5
Classifier: Programming Language :: Python :: 3.6
Classifier: Topic :: Office/Business :: Financial
Classifier: License :: OSI Approved :: MIT License
